hello_fish/__init__.py
hello_fish-0.1.0.dist-info/WHEEL
hello_fish-0.1.0.dist-info/METADATA
hello_fish-0.1.0.dist-info/RECORD
