Metadata-Version: 2.1
Name: hello-fish
Version: 0.1.0
Summary: Meu primeiro pacote, uma breve descrição de como ele funciona
Author: Marcus Pereira
Author-email: hi@marcuspereira.xyz
Requires-Python: >=3.8,<4.0
Classifier: Programming Language :: Python :: 3
Classifier: Programming Language :: Python :: 3.8
Classifier: Programming Language :: Python :: 3.9
